invisibleroads_macros_text/__init__.py
invisibleroads_macros_text-1.1.2.dist-info/METADATA
invisibleroads_macros_text-1.1.2.dist-info/WHEEL
invisibleroads_macros_text-1.1.2.dist-info/top_level.txt
invisibleroads_macros_text-1.1.2.dist-info/zip-safe
invisibleroads_macros_text-1.1.2.dist-info/RECORD
