Metadata-Version: 2.1
Name: invisibleroads-macros-text
Version: 1.1.2
Summary: Shortcut functions for text operations
Home-page: https://github.com/invisibleroads/invisibleroads-macros-text
Author: Roy Hyunjin Han
Author-email: rhh@crosscompute.com
License: UNKNOWN
Keywords: invisibleroads
Platform: UNKNOWN
Classifier: Programming Language :: Python
Classifier: License :: OSI Approved :: MIT License
Provides-Extra: test
Requires-Dist: pytest ; extra == 'test'
Requires-Dist: pytest-cov ; extra == 'test'
